edspdf_poppler-0.1.1.dist-info/METADATA
edspdf_poppler-0.1.1.dist-info/LICENSE
edspdf_poppler-0.1.1.dist-info/WHEEL
edspdf_poppler-0.1.1.dist-info/top_level.txt
edspdf_poppler-0.1.1.dist-info/RECORD
edspdf_poppler-0.1.1.dist-info/entry_points.txt
edspdf_poppler.libs/libfontconfig-42c558d2.so.1.11.1
edspdf_poppler.libs/libpng15-ce838cd1.so.15.13.0
edspdf_poppler.libs/libbz2-a273e504.so.1.0.6
edspdf_poppler.libs/libuuid-f64cda11.so.1.3.0
edspdf_poppler.libs/libfreetype-c0e61f0c.so.6.14.0
edspdf_poppler.libs/libpoppler-80d3393d.so.126.0.0
edspdf_poppler/bindings.cpp
edspdf_poppler/__init__.py
edspdf_poppler/bindings.cpython-310-x86_64-linux-gnu.so
