Metadata-Version: 2.1
Name: edspdf-poppler
Version: 0.1.1
Summary: Poppler extension for EDS-PDF
Author-email: Perceval Wajsbürt <perceval.wajsburt-ext@aphp.fr>
License:                     GNU GENERAL PUBLIC LICENSE
Project-URL: homepage, https://github.com/aphp/edspdf-poppler/
Project-URL: repository, https://github.com/aphp/edspdf-poppler/
Project-URL: documentation, https://aphp.github.io/edspdf-poppler/
Requires-Python: <4.0,>=3.7
Provides-Extra: dev
License-File: LICENSE
